{    
    "games":[
        {
            "Name": "Mario Kart Double Dash",
            "Developer": "Nintendo",
            "Publisher": "Nintendo",
            "Year": "2003",
            "System": "Game Cube",
            "Genre": "Racing",
            "Players": "1-4",
            "Screenshot": "games/MarioKartDoubleDash/img.png",
            "exe": "dolphin-emu -e games/MarioKartDoubleDash/mkdd.iso"
        },{
            "Name": "Alien Hominid",
            "Developer": "",
            "Publisher": "",
            "Year": "",
            "System": "Game Cube",
            "Genre": "",
            "Players": "",
            "Screenshot": "games/Untitled.png",
            "exe": "dolphin-emu -e games/AlienHominid/ah.gcm"
        },{
            "Name": "Jet Pac",
            "Developer": "Tim and Chris Stamper",
            "Publisher": "Ultimate Play the Game",
            "Year": "1983",
            "System": "ZX Spectrum",
            "Genre": "Shooter",
            "Players": "Single",
            "Screenshot": "games/JetPac/JetPac.png",
            "exe": "fuse games/JetPac/Jetpac.z80"
        },{
            "Name": "Zelda",
            "Developer": "Nintendo",
            "Publisher": "Nintendo",
            "Year": "",
            "System": "NES",
            "Genre": "Platformer",
            "Players": "1",
            "Screenshot": "games/Untitled.png",
            "exe": "fceux games/Zelda/zelda.nes"
        },{
            "Name": "Tetris",
            "Developer": "",
            "Publisher": "",
            "Year": "",
            "System": "NES",
            "Genre": "Puzzle",
            "Players": "1",
            "Screenshot": "games/Untitled.png",
            "exe": "fceux games/Tetris/tetris.nes"
        },{
            "Name": "PacMan",
            "Developer": "",
            "Publisher": "",
            "Year": "",
            "System": "NES",
            "Genre": "",
            "Players": "1",
            "Screenshot": "games/Untitled.png",
            "exe": "fceux games/PacMan/pacman.nes"
        },
        {
            "Name": "Mario Bros.",
            "Developer": "Nintendo",
            "Publisher": "Nintendo",
            "Year": "",
            "System": "NES",
            "Genre": "Platformer",
            "Players": "1",
            "Screenshot": "games/Untitled.png",
            "exe": "fceux games/MarioBros/MarioBro.nes"
        },{
            "Name": "Super Mario Bros. 2",
            "Developer": "Nintendo",
            "Publisher": "Nintendo",
            "Year": "",
            "System": "NES",
            "Genre": "Platformer",
            "Players": "1",
            "Screenshot": "games/Untitled.png",
            "exe": "fceux games/SuperMarioBros2/smb2.nes"
        },{
            "Name": "Super Mario Bros. 3",
            "Developer": "Nintendo",
            "Publisher": "Nintendo",
            "Year": "",
            "System": "NES",
            "Genre": "Platformer",
            "Players": "1",
            "Screenshot": "games/Untitled.png",
            "exe": "fceux games/SuperMarioBros3/smb3.nes"
        },{
            "Name": "Super Mario Bros.",
            "Developer": "Nintendo",
            "Publisher": "Nintendo",
            "Year": "1985",
            "System": "NES",
            "Genre": "Platformer",
            "Players": "1",
            "Screenshot": "games/SuperMarioBros/screenshot.png",
            "exe": "fceux games/SuperMarioBros/smb.nes"
        },{
            "Name": "Gauntlet",
            "Developer": "",
            "Publisher": "endo",
            "Year": "",
            "System": "NES",
            "Genre": "",
            "Players": "",
            "Screenshot": "games/Untitled.png",
            "exe": "fceux games/Gauntlet/Gauntlet.nes"
        },
        {
            "Name": "Bof Gm",
            "Developer": "Boffin Factory",
            "Publisher": "Boffin Factory",
            "Year": "2014",
            "System": "Boffin LARK",
            "Genre": "TBA",
            "Players": "TBA",
            "Screenshot": "games/BofGm/titleScreen.png",
            "exe": ""
        }
    ]

}